meggie_sourceanalysis/__init__.py
meggie_sourceanalysis/configuration.json
meggie_sourceanalysis/actions/__init__.py
meggie_sourceanalysis/actions/coregistration_coregister/__init__.py
meggie_sourceanalysis/actions/coregistration_coregister/configuration.json
meggie_sourceanalysis/actions/coregistration_delete/__init__.py
meggie_sourceanalysis/actions/coregistration_delete/configuration.json
meggie_sourceanalysis/actions/coregistration_info/__init__.py
meggie_sourceanalysis/actions/coregistration_info/configuration.json
meggie_sourceanalysis/actions/covariance_create/__init__.py
meggie_sourceanalysis/actions/covariance_create/configuration.json
meggie_sourceanalysis/actions/covariance_delete/__init__.py
meggie_sourceanalysis/actions/covariance_delete/configuration.json
meggie_sourceanalysis/actions/covariance_info/__init__.py
meggie_sourceanalysis/actions/covariance_info/configuration.json
meggie_sourceanalysis/actions/inverse_create/__init__.py
meggie_sourceanalysis/actions/inverse_create/configuration.json
meggie_sourceanalysis/actions/inverse_create/controller/inverse.py
meggie_sourceanalysis/actions/inverse_delete/__init__.py
meggie_sourceanalysis/actions/inverse_delete/configuration.json
meggie_sourceanalysis/actions/inverse_info/__init__.py
meggie_sourceanalysis/actions/inverse_info/configuration.json
meggie_sourceanalysis/actions/source_spectrum_create/__init__.py
meggie_sourceanalysis/actions/source_spectrum_create/configuration.json
meggie_sourceanalysis/actions/source_spectrum_create/controller/source_spectrum.py
meggie_sourceanalysis/actions/source_spectrum_delete/__init__.py
meggie_sourceanalysis/actions/source_spectrum_delete/configuration.json
meggie_sourceanalysis/actions/source_spectrum_info/__init__.py
meggie_sourceanalysis/actions/source_spectrum_info/configuration.json
meggie_sourceanalysis/actions/source_spectrum_plot/__init__.py
meggie_sourceanalysis/actions/source_spectrum_plot/configuration.json
meggie_sourceanalysis/datatypes/__init__.py
meggie_sourceanalysis-0.2.4.dist-info/METADATA
meggie_sourceanalysis-0.2.4.dist-info/WHEEL
meggie_sourceanalysis-0.2.4.dist-info/top_level.txt
meggie_sourceanalysis-0.2.4.dist-info/RECORD
