Metadata-Version: 2.2
Name: meggie_sourceanalysis
Version: 0.2.4
Summary: Source analysis plugin for Meggie
License: BSD
Project-URL: homepage, https://github.com/cibr-jyu/meggie_sourceanalysis
Requires-Dist: meggie>=1.9.0
Requires-Dist: pyvistaqt
Requires-Dist: nibabel
Requires-Dist: traitlets
Provides-Extra: dev
Requires-Dist: black; extra == "dev"
Requires-Dist: pylama; extra == "dev"
Requires-Dist: pytest; extra == "dev"
Requires-Dist: pytest-qt; extra == "dev"
Requires-Dist: build; extra == "dev"
Requires-Dist: twine; extra == "dev"
Requires-Dist: setuptools; extra == "dev"
Provides-Extra: test
Requires-Dist: black; extra == "test"
Requires-Dist: pylama; extra == "test"
Requires-Dist: pytest; extra == "test"
Requires-Dist: pytest-qt; extra == "test"
Requires-Dist: setuptools; extra == "test"
